zp_config/__init__.py
zp_config/config.py
zp_config-0.0.1.dist-info/METADATA
zp_config-0.0.1.dist-info/WHEEL
zp_config-0.0.1.dist-info/top_level.txt
zp_config-0.0.1.dist-info/RECORD
