Metadata-Version: 2.1
Name: zp-config
Version: 0.0.1
Summary: Config and secret package
Home-page: https://github.com/
Author: Ziuzin Pavel
Author-email: Ziuzin Pavel <zpavel.77@yandex.ru>
License: MIT
Classifier: Programming Language :: Python :: 3
Classifier: License :: OSI Approved :: MIT License
Classifier: Operating System :: OS Independent
Requires-Python: >=3.7
